{"cameraMode":{"drawMode":0,"name":"Shaded","section":"Shading Mode"},"sceneLighting":true,"audioPlay":false,"sceneViewState":{"m_AlwaysRefresh":false,"showFog":true,"showSkybox":true,"showFlares":true,"showImageEffects":true,"showParticleSystems":true,"showVisualEffectGraphs":true,"m_FxEnabled":true},"in2DMode":false,"pivot":{"x":4.318944931030273,"y":8.923452377319336,"z":-0.971605122089386},"rotation":{"x":-0.468610018491745,"y":0.01642743870615959,"z":-0.008716380223631859,"w":-0.8832063674926758},"size":1.4896202087402344,"orthographic":false}